{
  "generated_at": "2026-06-02T09:08:17.622987",
  "session": {
    "state": "manual_analyze",
    "stop_reason": "Manual Analyze Logs run",
    "warning": "",
    "elapsed_s": 0.0,
    "start_throttle_us": 0,
    "current_throttle_us": 0,
    "peak_throttle_us": 0
  },
  "coverage": {},
  "analysis": {
    "summary": "INAV-Toolkit: 18/100 (Needs attention. Focus on filters first, then PIDs.) | PID Roll: Delay 39ms; Pitch: Delay 64ms | PID plan: Roll P 30 -> 21 (-30%); Pitch P 40 -> 28 (-30%); Yaw P 35 -> 24 (-31%) | Notes: Minor imbalance (4.6%) - Motor 2 is the outlier | Top changes: Roll: Hover oscillation - reduce P from 30 to 21; Pitch: Hover oscillation - reduce P from 40 to 28; Yaw: Hover oscillation - reduce P from 35 to 24",
    "source": "D:\\Coding\\Python\\Modbus\\blackbox_imports\\LOG00001.01.csv",
    "pid_headline": "Recommended PID updates from Blackbox analysis.",
    "pid_highlights": [
      "Roll P 30 -> 21 (-30%)",
      "Pitch P 40 -> 28 (-30%)",
      "Yaw P 35 -> 24 (-31%)"
    ],
    "pid_cli": [
      "set mc_p_roll = 21",
      "set mc_p_pitch = 28",
      "set mc_p_yaw = 24",
      "save"
    ],
    "warnings": []
  },
  "log": {
    "csv_used": "D:\\Coding\\Python\\Modbus\\blackbox_imports\\LOG00001.01.csv",
    "rows": 113193,
    "duration_s": 114.607,
    "sample_rate_hz": 993.05,
    "peak_roll_error": 472.0,
    "peak_pitch_error": 432.0
  },
  "artifacts": {
    "combined_chart_sheet": "D:\\Coding\\Python\\Modbus\\blackbox_imports\\reports\\session_20260602_090806\\charts\\roll_trace_viewer.html",
    "trace_viewer": {
      "html": "D:\\Coding\\Python\\Modbus\\blackbox_imports\\reports\\session_20260602_090806\\charts\\roll_trace_viewer.html",
      "files": [
        "D:\\Coding\\Python\\Modbus\\blackbox_imports\\reports\\session_20260602_090806\\charts\\roll_trace_viewer.html"
      ],
      "warning": ""
    },
    "trace_viewers": {
      "roll": {
        "html": "D:\\Coding\\Python\\Modbus\\blackbox_imports\\reports\\session_20260602_090806\\charts\\roll_trace_viewer.html",
        "warning": ""
      },
      "pitch": {
        "html": "D:\\Coding\\Python\\Modbus\\blackbox_imports\\reports\\session_20260602_090806\\charts\\pitch_trace_viewer.html",
        "warning": ""
      },
      "files": [
        "D:\\Coding\\Python\\Modbus\\blackbox_imports\\reports\\session_20260602_090806\\charts\\roll_trace_viewer.html",
        "D:\\Coding\\Python\\Modbus\\blackbox_imports\\reports\\session_20260602_090806\\charts\\pitch_trace_viewer.html"
      ]
    }
  }
}